ceph_command_api/__init__.py
ceph_command_api/_generated.py
ceph_command_api-1.0.2.dist-info/DESCRIPTION.rst
ceph_command_api-1.0.2.dist-info/METADATA
ceph_command_api-1.0.2.dist-info/RECORD
ceph_command_api-1.0.2.dist-info/WHEEL
ceph_command_api-1.0.2.dist-info/metadata.json
ceph_command_api-1.0.2.dist-info/top_level.txt
