Metadata-Version: 2.0
Name: ceph-command-api
Version: 1.0.2
Summary: Automatically generated command API. 
Home-page: https://github.com/sebastian-philipp/ceph-command-api
Author: Sebastian Wagner
Author-email: sebastian.wagner@suse.com
License: UNKNOWN
Platform: UNKNOWN
Classifier: Intended Audience :: Developers
Classifier: Programming Language :: Python :: 3
Classifier: Programming Language :: Python :: 3.5
Classifier: Programming Language :: Python :: 3.6
Classifier: License :: OSI Approved :: GNU Lesser General Public License v2 or later (LGPLv2+)
Classifier: Operating System :: OS Independent
